{"frameRate":24,"armature":[{"aabb":{"width":196.94352742947626,"y":-533.5541364673636,"height":536.0803478178468,"x":-71.67636268708921},"type":"Armature","bone":[{"transform":{"y":-166.8785,"x":-73.5965},"name":"root"},{"length":52,"transform":{"skX":-104.4703,"y":-94.2256,"skY":-104.4703,"x":55.6063},"parent":"root","name":"Pelvis"},{"length":110,"transform":{"skX":19.4745,"y":-1.7585,"skY":19.4745,"x":49.6133},"parent":"Pelvis","name":"Waist"},{"length":131,"transform":{"skX":-177.9448,"y":0.1078,"skY":-177.9448,"x":15.8251},"parent":"Pelvis","name":"Thigh_F"},{"length":131,"transform":{"skX":-177.9448,"y":0.1078,"skY":-177.9448,"x":15.8251},"parent":"Pelvis","name":"Thigh_F1"},{"length":132,"transform":{"skX":23.6741,"skY":23.6741,"x":131.1673},"parent":"Thigh_F","name":"Shin_F"},{"length":132,"transform":{"skX":23.6741,"skY":23.6741,"x":131.1673},"parent":"Thigh_F1","name":"Shin_F1"},{"length":76,"transform":{"skX":65.533,"y":19.7653,"skY":65.533,"x":117.6224},"parent":"Waist","name":"Chest"},{"length":44,"transform":{"skX":23.2386,"y":0.4902,"skY":23.2386,"x":74.9176},"parent":"Chest","name":"Head"},{"length":119,"transform":{"skX":107.4705,"y":2.0892,"skY":107.4705,"x":8.9132},"parent":"Chest","name":"UpperArm_F"},{"length":42,"transform":{"skX":-90.8757,"skY":-90.8757,"x":132.3981},"parent":"Shin_F1","name":"Foot_F1"},{"length":42,"transform":{"skX":-90.8757,"skY":-90.8757,"x":132.3981},"parent":"Shin_F","name":"Foot_F"},{"length":119,"transform":{"skX":107.4705,"y":2.0892,"skY":107.4705,"x":8.9132},"parent":"Chest","name":"UpperArm_F1"},{"length":38,"transform":{"skX":-0.6494,"skY":-0.6494,"x":42.4451},"parent":"Foot_F1","name":"Toe_F1"},{"length":93,"transform":{"skX":-25.4122,"skY":-25.4122,"x":119.3722},"parent":"UpperArm_F","name":"bone"},{"length":38,"transform":{"skX":-0.6494,"skY":-0.6494,"x":42.4451},"parent":"Foot_F","name":"Toe_F"},{"length":93,"transform":{"skX":-27.783,"skY":-27.783,"x":119.3722},"parent":"UpperArm_F1","name":"bone2"},{"length":30,"transform":{"skX":24.1593,"skY":24.1593,"x":93.4354},"parent":"bone2","name":"bone11"}],"defaultActions":[{"gotoAndPlay":"Walk"}],"ik":[],"skin":[{"name":"","slot":[{"display":[{"type":"image","name":"Foot_F","transform":{"skX":-10.3833,"y":-3.6013,"skY":-10.3833,"x":11.4999}}],"name":"Foot_F"},{"display":[{"type":"image","name":"Chest","transform":{"skX":19.4628,"y":-11.5617,"skY":19.4628,"x":12.002}}],"name":"Chest"},{"display":[{"type":"image","name":"ForeArm_B_1","transform":{"skX":-60.2247,"y":0.8386,"skY":-60.2247,"x":54.1246}}],"name":"ForeArm_F1"},{"display":[{"type":"image","name":"Thigh_F","transform":{"skX":-77.5849,"y":-2.6335,"skY":-77.5849,"x":70.6687}}],"name":"Thigh_F"},{"display":[{"type":"image","name":"Hand_B_1","transform":{"skX":-84.384,"y":0.7566,"skY":-84.384,"x":37.8577}}],"name":"Hand_F1"},{"display":[{"type":"image","name":"Shin_B_1","transform":{"skX":-101.259,"y":-4.0017,"skY":-101.259,"x":58.2659}}],"name":"Shin_F1"},{"display":[{"type":"image","name":"ArmCannon","transform":{"skX":-0.5705,"y":8.7612,"skY":-0.5705,"x":71.5568}}],"name":"ArmCannon"},{"display":[{"type":"image","name":"Toe_F","transform":{"skX":-9.7339,"y":-1.831,"skY":-9.7339,"x":15.7013}}],"name":"Toe_F"},{"display":[{"type":"image","name":"Head","transform":{"skX":-3.7758,"y":3.5521,"skY":-3.7758,"x":16.7889}}],"name":"Head"},{"display":[{"type":"image","name":"Toe_B_1","transform":{"skX":-9.7339,"y":-1.831,"skY":-9.7339,"x":15.7013}}],"name":"Toe_F1"},{"display":[{"type":"image","name":"UpperArm_F","transform":{"skX":-88.0077,"y":-3.3821,"skY":-88.0077,"x":68.3089}}],"name":"UpperArm_F"},{"display":[{"type":"image","name":"Pelvis","transform":{"skX":104.4703,"y":3.0173,"skY":104.4703,"x":30.1009}}],"name":"Pelvis"},{"display":[{"type":"image","name":"UpperArm_B_1","transform":{"skX":-88.0077,"y":-3.3821,"skY":-88.0077,"x":68.3089}}],"name":"UpperArm_F1"},{"display":[{"type":"image","name":"Thigh_B_1","transform":{"skX":-77.5849,"y":-2.6335,"skY":-77.5849,"x":70.6687}}],"name":"Thigh_F1"},{"display":[{"type":"image","name":"Shin_F","transform":{"skX":-101.259,"y":-4.0017,"skY":-101.259,"x":58.2659}}],"name":"Shin_F"},{"display":[{"type":"image","name":"Waist","transform":{"skX":84.9958,"y":15.9823,"skY":84.9958,"x":41.0255}}],"name":"Waist"},{"display":[{"type":"image","name":"Foot_B_1","transform":{"skX":-10.3833,"y":-3.6013,"skY":-10.3833,"x":11.4999}}],"name":"Foot_F1"}]}],"animation":[{"frame":[],"ffd":[],"slot":[{"frame":[{"curve":[0.5,0,0.5,1],"duration":4},{"curve":[0.5,0,0.5,1],"duration":2},{"curve":[0.5,0,0.5,1],"duration":4},{"curve":[0.5,0,0.5,1],"duration":2},{"curve":[0.5,0,0.5,1],"duration":4},{"curve":[0.5,0,0.5,1],"duration":2},{"curve":[0.5,0,0.5,1],"duration":4},{"curve":[0.5,0,0.5,1],"duration":2},{"tweenEasing":null,"curve":[0.5,0,0.5,1],"duration":0}],"name":"Thigh_F1"},{"frame":[{"curve":[0.5,0,0.5,1],"duration":4},{"curve":[0.5,0,0.5,1],"duration":2},{"curve":[0.5,0,0.5,1],"duration":4},{"curve":[0.5,0,0.5,1],"duration":2},{"curve":[0.5,0,0.5,1],"duration":4},{"curve":[0.5,0,0.5,1],"duration":2},{"curve":[0.5,0,0.5,1],"duration":4},{"curve":[0.5,0,0.5,1],"duration":2},{"tweenEasing":null,"curve":[0.5,0,0.5,1],"duration":0}],"name":"Shin_F1"},{"frame":[{"curve":[0.5,0,0.5,1],"duration":4},{"curve":[0.5,0,0.5,1],"duration":2},{"curve":[0.5,0,0.5,1],"duration":4},{"curve":[0.5,0,0.5,1],"duration":2},{"curve":[0.5,0,0.5,1],"duration":4},{"curve":[0.5,0,0.5,1],"duration":2},{"curve":[0.5,0,0.5,1],"duration":4},{"curve":[0.5,0,0.5,1],"duration":2},{"tweenEasing":null,"curve":[0.5,0,0.5,1],"duration":0}],"name":"Foot_F1"},{"frame":[{"curve":[0.5,0,0.5,1],"duration":4},{"curve":[0.5,0,0.5,1],"duration":2},{"curve":[0.5,0,0.5,1],"duration":4},{"curve":[0.5,0,0.5,1],"duration":2},{"curve":[0.5,0,0.5,1],"duration":4},{"curve":[0.5,0,0.5,1],"duration":2},{"curve":[0.5,0,0.5,1],"duration":4},{"curve":[0.5,0,0.5,1],"duration":2},{"tweenEasing":null,"curve":[0.5,0,0.5,1],"duration":0}],"name":"Toe_F1"},{"frame":[{"curve":[0.5,0,0.5,1],"duration":4},{"curve":[0.5,0,0.5,1],"duration":2},{"curve":[0.5,0,0.5,1],"duration":4},{"curve":[0.5,0,0.5,1],"duration":2},{"curve":[0.5,0,0.5,1],"duration":4},{"curve":[0.5,0,0.5,1],"duration":2},{"curve":[0.5,0,0.5,1],"duration":4},{"curve":[0.5,0,0.5,1],"duration":2},{"tweenEasing":null,"curve":[0.5,0,0.5,1],"duration":0}],"name":"ForeArm_F1"},{"frame":[{"curve":[0.5,0,0.5,1],"duration":4},{"curve":[0.5,0,0.5,1],"duration":2},{"curve":[0.5,0,0.5,1],"duration":4},{"curve":[0.5,0,0.5,1],"duration":2},{"curve":[0.5,0,0.5,1],"duration":4},{"curve":[0.5,0,0.5,1],"duration":2},{"curve":[0.5,0,0.5,1],"duration":4},{"curve":[0.5,0,0.5,1],"duration":2},{"tweenEasing":null,"curve":[0.5,0,0.5,1],"duration":0}],"name":"UpperArm_F1"},{"frame":[{"curve":[0.5,0,0.5,1],"duration":4},{"curve":[0.5,0,0.5,1],"duration":2},{"curve":[0.5,0,0.5,1],"duration":4},{"curve":[0.5,0,0.5,1],"duration":2},{"curve":[0.5,0,0.5,1],"duration":4},{"curve":[0.5,0,0.5,1],"duration":2},{"curve":[0.5,0,0.5,1],"duration":4},{"curve":[0.5,0,0.5,1],"duration":2},{"tweenEasing":null,"curve":[0.5,0,0.5,1],"duration":0}],"name":"Hand_F1"},{"frame":[{"curve":[0.5,0,0.5,1],"duration":6},{"curve":[0.5,0,0.5,1],"duration":6},{"curve":[0.5,0,0.5,1],"duration":6},{"curve":[0.5,0,0.5,1],"duration":6},{"tweenEasing":null,"curve":[0.5,0,0.5,1],"duration":0}],"name":"Waist"},{"frame":[{"curve":[0.5,0,0.5,1],"duration":6},{"curve":[0.5,0,0.5,1],"duration":6},{"curve":[0.5,0,0.5,1],"duration":6},{"curve":[0.5,0,0.5,1],"duration":6},{"tweenEasing":null,"curve":[0.5,0,0.5,1],"duration":0}],"name":"Head"},{"frame":[{"curve":[0.5,0,0.5,1],"duration":6},{"curve":[0.5,0,0.5,1],"duration":6},{"curve":[0.5,0,0.5,1],"duration":6},{"curve":[0.5,0,0.5,1],"duration":6},{"tweenEasing":null,"curve":[0.5,0,0.5,1],"duration":0}],"name":"Chest"},{"frame":[{"curve":[0.5,0,0.5,1],"duration":4},{"curve":[0.5,0,0.5,1],"duration":2},{"curve":[0.5,0,0.5,1],"duration":4},{"curve":[0.5,0,0.5,1],"duration":2},{"curve":[0.5,0,0.5,1],"duration":4},{"curve":[0.5,0,0.5,1],"duration":2},{"curve":[0.5,0,0.5,1],"duration":4},{"curve":[0.5,0,0.5,1],"duration":2},{"tweenEasing":null,"curve":[0.5,0,0.5,1],"duration":0}],"name":"Pelvis"},{"frame":[{"curve":[0.5,0,0.5,1],"duration":4},{"curve":[0.5,0,0.5,1],"duration":2},{"curve":[0.5,0,0.5,1],"duration":4},{"curve":[0.5,0,0.5,1],"duration":2},{"curve":[0.5,0,0.5,1],"duration":4},{"curve":[0.5,0,0.5,1],"duration":2},{"curve":[0.5,0,0.5,1],"duration":4},{"curve":[0.5,0,0.5,1],"duration":2},{"tweenEasing":null,"curve":[0.5,0,0.5,1],"duration":0}],"name":"Thigh_F"},{"frame":[{"curve":[0.5,0,0.5,1],"duration":4},{"curve":[0.5,0,0.5,1],"duration":2},{"curve":[0.5,0,0.5,1],"duration":4},{"curve":[0.5,0,0.5,1],"duration":2},{"curve":[0.5,0,0.5,1],"duration":4},{"curve":[0.5,0,0.5,1],"duration":2},{"curve":[0.5,0,0.5,1],"duration":4},{"curve":[0.5,0,0.5,1],"duration":2},{"tweenEasing":null,"curve":[0.5,0,0.5,1],"duration":0}],"name":"Shin_F"},{"frame":[{"curve":[0.5,0,0.5,1],"duration":4},{"curve":[0.5,0,0.5,1],"duration":2},{"curve":[0.5,0,0.5,1],"duration":4},{"curve":[0.5,0,0.5,1],"duration":2},{"curve":[0.5,0,0.5,1],"duration":4},{"curve":[0.5,0,0.5,1],"duration":2},{"curve":[0.5,0,0.5,1],"duration":4},{"curve":[0.5,0,0.5,1],"duration":2},{"tweenEasing":null,"curve":[0.5,0,0.5,1],"duration":0}],"name":"Toe_F"},{"frame":[{"curve":[0.5,0,0.5,1],"duration":4},{"curve":[0.5,0,0.5,1],"duration":2},{"curve":[0.5,0,0.5,1],"duration":4},{"curve":[0.5,0,0.5,1],"duration":2},{"curve":[0.5,0,0.5,1],"duration":4},{"curve":[0.5,0,0.5,1],"duration":2},{"curve":[0.5,0,0.5,1],"duration":4},{"curve":[0.5,0,0.5,1],"duration":2},{"tweenEasing":null,"curve":[0.5,0,0.5,1],"duration":0}],"name":"Foot_F"},{"frame":[{"curve":[0.5,0,0.5,1],"duration":4},{"curve":[0.5,0,0.5,1],"duration":2},{"curve":[0.5,0,0.5,1],"duration":4},{"curve":[0.5,0,0.5,1],"duration":2},{"curve":[0.5,0,0.5,1],"duration":4},{"curve":[0.5,0,0.5,1],"duration":2},{"curve":[0.5,0,0.5,1],"duration":4},{"curve":[0.5,0,0.5,1],"duration":2},{"tweenEasing":null,"curve":[0.5,0,0.5,1],"duration":0}],"name":"UpperArm_F"}],"bone":[{"frame":[{"curve":[0.5,0,0.5,1],"duration":4,"transform":{"y":27.7657}},{"curve":[0.5,0,0.5,1],"duration":2,"transform":{"y":7.2885}},{"curve":[0.5,0,0.5,1],"duration":4,"transform":{"y":-10.1094}},{"curve":[0.5,0,0.5,1],"duration":2,"transform":{"y":18.0477}},{"curve":[0.5,0,0.5,1],"duration":4,"transform":{"y":27.7657}},{"curve":[0.5,0,0.5,1],"duration":2,"transform":{"y":7.2885}},{"curve":[0.5,0,0.5,1],"duration":4,"transform":{"y":-10.1094}},{"curve":[0.5,0,0.5,1],"duration":2,"transform":{"y":18.0477}},{"tweenEasing":null,"duration":0,"transform":{"y":27.7657}}],"name":"root"},{"frame":[{"curve":[0.5,0,0.5,1],"duration":4,"transform":{}},{"curve":[0.5,0,0.5,1],"duration":2,"transform":{}},{"curve":[0.5,0,0.5,1],"duration":4,"transform":{}},{"curve":[0.5,0,0.5,1],"duration":2,"transform":{}},{"curve":[0.5,0,0.5,1],"duration":4,"transform":{}},{"curve":[0.5,0,0.5,1],"duration":2,"transform":{}},{"curve":[0.5,0,0.5,1],"duration":4,"transform":{}},{"curve":[0.5,0,0.5,1],"duration":2,"transform":{}},{"tweenEasing":null,"duration":0,"transform":{}}],"name":"Pelvis"},{"frame":[{"curve":[0.5,0,0.5,1],"duration":6,"transform":{"skX":6.3085,"skY":6.3085}},{"curve":[0.5,0,0.5,1],"duration":6,"transform":{"skX":-4.4071,"skY":-4.4071}},{"curve":[0.5,0,0.5,1],"duration":6,"transform":{"skX":6.3085,"skY":6.3085}},{"curve":[0.5,0,0.5,1],"duration":6,"transform":{"skX":-4.4071,"skY":-4.4071}},{"tweenEasing":null,"duration":0,"transform":{"skX":6.3085,"skY":6.3085}}],"name":"Waist"},{"frame":[{"curve":[0.5,0,0.5,1],"duration":4,"transform":{"skX":21.4323,"skY":21.4323}},{"curve":[0.5,0,0.5,1],"duration":2,"transform":{"skX":-9.6426,"skY":-9.6426}},{"curve":[0.5,0,0.5,1],"duration":4,"transform":{"skX":-38.2726,"skY":-38.2726}},{"curve":[0.5,0,0.5,1],"duration":2,"transform":{"skX":-25.3675,"skY":-25.3675}},{"curve":[0.5,0,0.5,1],"duration":4,"transform":{"skX":-26.9517,"skY":-26.9517}},{"curve":[0.5,0,0.5,1],"duration":2,"transform":{"skX":1.7511,"skY":1.7511}},{"curve":[0.5,0,0.5,1],"duration":4,"transform":{"skX":28.7458,"skY":28.7458}},{"curve":[0.5,0,0.5,1],"duration":2,"transform":{"skX":25.3272,"skY":25.3272}},{"tweenEasing":null,"duration":0,"transform":{"skX":21.4323,"skY":21.4323}}],"name":"Thigh_F"},{"frame":[{"curve":[0.5,0,0.5,1],"duration":4,"transform":{"skX":-26.9517,"skY":-26.9517}},{"curve":[0.5,0,0.5,1],"duration":2,"transform":{"skX":1.7511,"skY":1.7511}},{"curve":[0.5,0,0.5,1],"duration":4,"transform":{"skX":28.7458,"skY":28.7458}},{"curve":[0.5,0,0.5,1],"duration":2,"transform":{"skX":25.3272,"skY":25.3272}},{"curve":[0.5,0,0.5,1],"duration":4,"transform":{"skX":21.4323,"skY":21.4323}},{"curve":[0.5,0,0.5,1],"duration":2,"transform":{"skX":-9.6426,"skY":-9.6426}},{"curve":[0.5,0,0.5,1],"duration":4,"transform":{"skX":-38.2726,"skY":-38.2726}},{"curve":[0.5,0,0.5,1],"duration":2,"transform":{"skX":-25.3675,"skY":-25.3675}},{"tweenEasing":null,"duration":0,"transform":{"skX":-26.9517,"skY":-26.9517}}],"name":"Thigh_F1"},{"frame":[{"curve":[0.5,0,0.5,1],"duration":6,"transform":{"skX":-10.8128,"skY":-10.8128}},{"curve":[0.5,0,0.5,1],"duration":6,"transform":{"skX":3.3353,"skY":3.3353}},{"curve":[0.5,0,0.5,1],"duration":6,"transform":{"skX":-10.8128,"skY":-10.8128}},{"curve":[0.5,0,0.5,1],"duration":6,"transform":{"skX":3.3353,"skY":3.3353}},{"tweenEasing":null,"duration":0,"transform":{"skX":-10.8128,"skY":-10.8128}}],"name":"Chest"},{"frame":[{"curve":[0.5,0,0.5,1],"duration":4,"transform":{"skX":2.781,"skY":2.781}},{"curve":[0.5,0,0.5,1],"duration":2,"transform":{"skX":12.173,"skY":12.173}},{"curve":[0.5,0,0.5,1],"duration":4,"transform":{"skX":-8.5017,"skY":-8.5017}},{"curve":[0.5,0,0.5,1],"duration":2,"transform":{"skX":11.1239,"skY":11.1239}},{"curve":[0.5,0,0.5,1],"duration":4,"transform":{"skX":21.6437,"skY":21.6437}},{"curve":[0.5,0,0.5,1],"duration":2,"transform":{"skX":60.9022,"skY":60.9022}},{"curve":[0.5,0,0.5,1],"duration":4,"transform":{"skX":60.7857,"skY":60.7857}},{"curve":[0.5,0,0.5,1],"duration":2,"transform":{}},{"tweenEasing":null,"duration":0,"transform":{"skX":2.781,"skY":2.781}}],"name":"Shin_F1"},{"frame":[{"curve":[0.5,0,0.5,1],"duration":4,"transform":{"skX":21.6437,"skY":21.6437}},{"curve":[0.5,0,0.5,1],"duration":2,"transform":{"skX":60.9022,"skY":60.9022}},{"curve":[0.5,0,0.5,1],"duration":4,"transform":{"skX":60.7857,"skY":60.7857}},{"curve":[0.5,0,0.5,1],"duration":2,"transform":{}},{"curve":[0.5,0,0.5,1],"duration":4,"transform":{"skX":2.781,"skY":2.781}},{"curve":[0.5,0,0.5,1],"duration":2,"transform":{"skX":12.173,"skY":12.173}},{"curve":[0.5,0,0.5,1],"duration":4,"transform":{"skX":-8.5017,"skY":-8.5017}},{"curve":[0.5,0,0.5,1],"duration":2,"transform":{"skX":11.1239,"skY":11.1239}},{"tweenEasing":null,"duration":0,"transform":{"skX":21.6437,"skY":21.6437}}],"name":"Shin_F"},{"frame":[{"curve":[0.5,0,0.5,1],"duration":6,"transform":{"skX":-0.2728,"skY":-0.2728}},{"curve":[0.5,0,0.5,1],"duration":6,"transform":{"skX":3.0758,"skY":3.0758}},{"curve":[0.5,0,0.5,1],"duration":6,"transform":{"skX":-0.2728,"skY":-0.2728}},{"curve":[0.5,0,0.5,1],"duration":6,"transform":{"skX":3.0758,"skY":3.0758}},{"tweenEasing":null,"duration":0,"transform":{"skX":-0.2728,"skY":-0.2728}}],"name":"Head"},{"frame":[{"curve":[0.5,0,0.5,1],"duration":4,"transform":{"skX":-13.3861,"skY":-13.3861}},{"curve":[0.5,0,0.5,1],"duration":2,"transform":{"skX":4.0341,"skY":4.0341}},{"curve":[0.5,0,0.5,1],"duration":4,"transform":{"skX":21.4544,"skY":21.4544}},{"curve":[0.5,0,0.5,1],"duration":2,"transform":{"skX":38.8746,"skY":38.8746}},{"curve":[0.5,0,0.5,1],"duration":4,"transform":{"skX":42.887,"skY":42.887}},{"curve":[0.5,0,0.5,1],"duration":2,"transform":{"skX":27.3859,"skY":27.3859}},{"curve":[0.5,0,0.5,1],"duration":4,"transform":{"skX":11.8849,"skY":11.8849}},{"curve":[0.5,0,0.5,1],"duration":2,"transform":{"skX":-3.6162,"skY":-3.6162}},{"tweenEasing":null,"duration":0,"transform":{"skX":-13.3861,"skY":-13.3861}}],"name":"UpperArm_F"},{"frame":[{"curve":[0.5,0,0.5,1],"duration":4,"transform":{"skX":22.6145,"skY":22.6145}},{"curve":[0.5,0,0.5,1],"duration":2,"transform":{"skX":-12.3399,"skY":-12.3399}},{"curve":[0.5,0,0.5,1],"duration":4,"transform":{"skX":24.4409,"skY":24.4409}},{"curve":[0.5,0,0.5,1],"duration":2,"transform":{}},{"curve":[0.5,0,0.5,1],"duration":4,"transform":{"skX":-1.9274,"skY":-1.9274}},{"curve":[0.5,0,0.5,1],"duration":2,"transform":{"skX":-3.8549,"skY":-3.8549}},{"curve":[0.5,0,0.5,1],"duration":4,"transform":{"skX":21.8138,"skY":21.8138}},{"curve":[0.5,0,0.5,1],"duration":2,"transform":{"skX":-7.7098,"skY":-7.7098}},{"tweenEasing":null,"duration":0,"transform":{"skX":22.6145,"skY":22.6145}}],"name":"Foot_F1"},{"frame":[{"curve":[0.5,0,0.5,1],"duration":4,"transform":{"skX":-1.9274,"skY":-1.9274}},{"curve":[0.5,0,0.5,1],"duration":2,"transform":{"skX":-3.8549,"skY":-3.8549}},{"curve":[0.5,0,0.5,1],"duration":4,"transform":{"skX":21.8138,"skY":21.8138}},{"curve":[0.5,0,0.5,1],"duration":2,"transform":{"skX":-7.7098,"skY":-7.7098}},{"curve":[0.5,0,0.5,1],"duration":4,"transform":{"skX":22.6145,"skY":22.6145}},{"curve":[0.5,0,0.5,1],"duration":2,"transform":{"skX":-12.3399,"skY":-12.3399}},{"curve":[0.5,0,0.5,1],"duration":4,"transform":{"skX":24.4409,"skY":24.4409}},{"curve":[0.5,0,0.5,1],"duration":2,"transform":{}},{"tweenEasing":null,"duration":0,"transform":{"skX":-1.9274,"skY":-1.9274}}],"name":"Foot_F"},{"frame":[{"curve":[0.5,0,0.5,1],"duration":4,"transform":{"skX":42.887,"skY":42.887}},{"curve":[0.5,0,0.5,1],"duration":2,"transform":{"skX":27.3859,"skY":27.3859}},{"curve":[0.5,0,0.5,1],"duration":4,"transform":{"skX":11.8849,"skY":11.8849}},{"curve":[0.5,0,0.5,1],"duration":2,"transform":{"skX":-3.6162,"skY":-3.6162}},{"curve":[0.5,0,0.5,1],"duration":4,"transform":{"skX":-13.3861,"skY":-13.3861}},{"curve":[0.5,0,0.5,1],"duration":2,"transform":{"skX":4.0341,"skY":4.0341}},{"curve":[0.5,0,0.5,1],"duration":4,"transform":{"skX":21.4544,"skY":21.4544}},{"curve":[0.5,0,0.5,1],"duration":2,"transform":{"skX":38.8746,"skY":38.8746}},{"tweenEasing":null,"duration":0,"transform":{"skX":42.887,"skY":42.887}}],"name":"UpperArm_F1"},{"frame":[{"curve":[0.5,0,0.5,1],"duration":4,"transform":{}},{"curve":[0.5,0,0.5,1],"duration":2,"transform":{"skX":41.2448,"skY":41.2448}},{"curve":[0.5,0,0.5,1],"duration":4,"transform":{"skX":32.1238,"skY":32.1238}},{"curve":[0.5,0,0.5,1],"duration":2,"transform":{}},{"curve":[0.5,0,0.5,1],"duration":4,"transform":{}},{"curve":[0.5,0,0.5,1],"duration":2,"transform":{}},{"curve":[0.5,0,0.5,1],"duration":4,"transform":{}},{"curve":[0.5,0,0.5,1],"duration":2,"transform":{}},{"tweenEasing":null,"duration":0,"transform":{}}],"name":"bone2"},{"frame":[{"curve":[0.5,0,0.5,1],"duration":4,"transform":{}},{"curve":[0.5,0,0.5,1],"duration":2,"transform":{}},{"curve":[0.5,0,0.5,1],"duration":4,"transform":{}},{"curve":[0.5,0,0.5,1],"duration":2,"transform":{}},{"curve":[0.5,0,0.5,1],"duration":4,"transform":{}},{"curve":[0.5,0,0.5,1],"duration":2,"transform":{"skX":41.2448,"skY":41.2448}},{"curve":[0.5,0,0.5,1],"duration":4,"transform":{"skX":32.1238,"skY":32.1238}},{"curve":[0.5,0,0.5,1],"duration":2,"transform":{}},{"tweenEasing":null,"duration":0,"transform":{}}],"name":"bone"},{"frame":[{"curve":[0.5,0,0.5,1],"duration":4,"transform":{"skX":-45.8063,"skY":-45.8063}},{"curve":[0.5,0,0.5,1],"duration":2,"transform":{"skX":-30.5376,"skY":-30.5376}},{"curve":[0.5,0,0.5,1],"duration":4,"transform":{"skX":-15.2688,"skY":-15.2688}},{"curve":[0.5,0,0.5,1],"duration":2,"transform":{}},{"curve":[0.5,0,0.5,1],"duration":4,"transform":{"skX":2.5555,"skY":2.5555}},{"curve":[0.5,0,0.5,1],"duration":2,"transform":{"skX":-1.6685,"skY":-1.6685}},{"curve":[0.5,0,0.5,1],"duration":4,"transform":{"skX":-40.1236,"skY":-40.1236}},{"curve":[0.5,0,0.5,1],"duration":2,"transform":{"skX":-33.2013,"skY":-33.2013}},{"tweenEasing":null,"duration":0,"transform":{"skX":-45.8063,"skY":-45.8063}}],"name":"Toe_F"},{"frame":[{"curve":[0.5,0,0.5,1],"duration":4,"transform":{"skX":2.5555,"skY":2.5555}},{"curve":[0.5,0,0.5,1],"duration":2,"transform":{"skX":-1.6685,"skY":-1.6685}},{"curve":[0.5,0,0.5,1],"duration":4,"transform":{"skX":-40.1236,"skY":-40.1236}},{"curve":[0.5,0,0.5,1],"duration":2,"transform":{"skX":-33.2013,"skY":-33.2013}},{"curve":[0.5,0,0.5,1],"duration":4,"transform":{"skX":-45.8063,"skY":-45.8063}},{"curve":[0.5,0,0.5,1],"duration":2,"transform":{"skX":-30.5376,"skY":-30.5376}},{"curve":[0.5,0,0.5,1],"duration":4,"transform":{"skX":-15.2688,"skY":-15.2688}},{"curve":[0.5,0,0.5,1],"duration":2,"transform":{}},{"tweenEasing":null,"duration":0,"transform":{"skX":2.5555,"skY":2.5555}}],"name":"Toe_F1"},{"frame":[{"curve":[0.5,0,0.5,1],"duration":4,"transform":{}},{"curve":[0.5,0,0.5,1],"duration":2,"transform":{}},{"curve":[0.5,0,0.5,1],"duration":4,"transform":{}},{"curve":[0.5,0,0.5,1],"duration":2,"transform":{}},{"curve":[0.5,0,0.5,1],"duration":4,"transform":{}},{"curve":[0.5,0,0.5,1],"duration":2,"transform":{}},{"curve":[0.5,0,0.5,1],"duration":4,"transform":{}},{"curve":[0.5,0,0.5,1],"duration":2,"transform":{}},{"tweenEasing":null,"duration":0,"transform":{}}],"name":"bone11"}],"playTimes":0,"name":"Walk","duration":24},{"frame":[],"ffd":[],"slot":[{"frame":[{"tweenEasing":null,"curve":[0.5,0,0.5,1],"duration":0}],"name":"Thigh_F1"},{"frame":[{"tweenEasing":null,"curve":[0.5,0,0.5,1],"duration":0}],"name":"Shin_F1"},{"frame":[{"tweenEasing":null,"curve":[0.5,0,0.5,1],"duration":0}],"name":"Foot_F1"},{"frame":[{"tweenEasing":null,"curve":[0.5,0,0.5,1],"duration":0}],"name":"Toe_F1"},{"frame":[{"tweenEasing":null,"curve":[0.5,0,0.5,1],"duration":0}],"name":"ForeArm_F1"},{"frame":[{"tweenEasing":null,"curve":[0.5,0,0.5,1],"duration":0}],"name":"UpperArm_F1"},{"frame":[{"tweenEasing":null,"curve":[0.5,0,0.5,1],"duration":0}],"name":"Hand_F1"},{"frame":[{"tweenEasing":null,"curve":[0.5,0,0.5,1],"duration":0}],"name":"Waist"},{"frame":[{"tweenEasing":null,"curve":[0.5,0,0.5,1],"duration":0}],"name":"Head"},{"frame":[{"tweenEasing":null,"curve":[0.5,0,0.5,1],"duration":0}],"name":"Chest"},{"frame":[{"tweenEasing":null,"curve":[0.5,0,0.5,1],"duration":0}],"name":"Pelvis"},{"frame":[{"tweenEasing":null,"curve":[0.5,0,0.5,1],"duration":0}],"name":"Thigh_F"},{"frame":[{"tweenEasing":null,"curve":[0.5,0,0.5,1],"duration":0}],"name":"Shin_F"},{"frame":[{"tweenEasing":null,"curve":[0.5,0,0.5,1],"duration":0}],"name":"Toe_F"},{"frame":[{"tweenEasing":null,"curve":[0.5,0,0.5,1],"duration":0}],"name":"Foot_F"},{"frame":[{"tweenEasing":null,"curve":[0.5,0,0.5,1],"duration":0}],"name":"UpperArm_F"}],"bone":[{"frame":[{"tweenEasing":null,"duration":0,"transform":{"y":27.7657}}],"name":"root"},{"frame":[{"tweenEasing":null,"duration":0,"transform":{}}],"name":"Pelvis"},{"frame":[{"tweenEasing":null,"duration":0,"transform":{"skX":6.3085,"skY":6.3085}}],"name":"Waist"},{"frame":[{"tweenEasing":null,"duration":0,"transform":{"skX":21.4323,"skY":21.4323}}],"name":"Thigh_F"},{"frame":[{"tweenEasing":null,"duration":0,"transform":{"skX":-26.9517,"skY":-26.9517}}],"name":"Thigh_F1"},{"frame":[{"tweenEasing":null,"duration":0,"transform":{"skX":-10.8128,"skY":-10.8128}}],"name":"Chest"},{"frame":[{"tweenEasing":null,"duration":0,"transform":{"skX":2.781,"skY":2.781}}],"name":"Shin_F1"},{"frame":[{"tweenEasing":null,"duration":0,"transform":{"skX":21.6437,"skY":21.6437}}],"name":"Shin_F"},{"frame":[{"tweenEasing":null,"duration":0,"transform":{"skX":-0.2728,"skY":-0.2728}}],"name":"Head"},{"frame":[{"tweenEasing":null,"duration":0,"transform":{"skX":-13.3861,"skY":-13.3861}}],"name":"UpperArm_F"},{"frame":[{"tweenEasing":null,"duration":0,"transform":{"skX":22.6145,"skY":22.6145}}],"name":"Foot_F1"},{"frame":[{"tweenEasing":null,"duration":0,"transform":{"skX":-1.9274,"skY":-1.9274}}],"name":"Foot_F"},{"frame":[{"tweenEasing":null,"duration":0,"transform":{"skX":42.887,"skY":42.887}}],"name":"UpperArm_F1"},{"frame":[{"tweenEasing":null,"duration":0,"transform":{}}],"name":"bone2"},{"frame":[{"tweenEasing":null,"duration":0,"transform":{"skX":-79.5473,"skY":-79.5473}}],"name":"bone"},{"frame":[{"tweenEasing":null,"duration":0,"transform":{"skX":-45.8063,"skY":-45.8063}}],"name":"Toe_F"},{"frame":[{"tweenEasing":null,"duration":0,"transform":{"skX":2.5555,"skY":2.5555}}],"name":"Toe_F1"},{"frame":[{"tweenEasing":null,"duration":0,"transform":{}}],"name":"bone11"}],"playTimes":0,"name":"Shoot","duration":0}],"frameRate":24,"name":"Armature","slot":[{"color":{},"name":"Thigh_F1","parent":"Thigh_F1"},{"z":1,"color":{},"name":"Shin_F1","parent":"Shin_F1"},{"z":2,"color":{},"name":"Foot_F1","parent":"Foot_F1"},{"z":3,"color":{},"name":"Toe_F1","parent":"Toe_F1"},{"z":4,"color":{},"name":"ForeArm_F1","parent":"bone2"},{"z":5,"color":{},"name":"UpperArm_F1","parent":"UpperArm_F1"},{"z":6,"color":{},"name":"Hand_F1","parent":"bone11"},{"z":7,"color":{},"name":"Waist","parent":"Waist"},{"z":8,"color":{},"name":"Head","parent":"Head"},{"z":9,"color":{},"name":"Chest","parent":"Chest"},{"z":10,"color":{},"name":"Pelvis","parent":"Pelvis"},{"z":11,"color":{},"name":"Thigh_F","parent":"Thigh_F"},{"z":12,"color":{},"name":"Shin_F","parent":"Shin_F"},{"z":13,"color":{},"name":"Toe_F","parent":"Toe_F"},{"z":14,"color":{},"name":"Foot_F","parent":"Foot_F"},{"z":15,"color":{},"name":"UpperArm_F","parent":"UpperArm_F"},{"z":16,"color":{},"name":"ArmCannon","parent":"bone"}]}],"isGlobal":0,"name":"SkellingtonRed","version":"5.0"}